builder2ibek/__init__.py
builder2ibek/__main__.py
builder2ibek/_version.py
builder2ibek/builder.py
builder2ibek/convert.py
builder2ibek/db2autosave.py
builder2ibek/dbcompare.py
builder2ibek/moduleinfos.py
builder2ibek/types.py
builder2ibek/utils.py
builder2ibek/converters/ADAravis.py
builder2ibek/converters/ADZMQ.py
builder2ibek/converters/BL20J.py
builder2ibek/converters/BL46P-BUILDER.py
builder2ibek/converters/DLS8515.py
builder2ibek/converters/Hy8401ip.py
builder2ibek/converters/Hy8402ip.py
builder2ibek/converters/IOCInfo.py
builder2ibek/converters/OXCS700.py
builder2ibek/converters/OXCS700asyn.py
builder2ibek/converters/README.md
builder2ibek/converters/SchottLLS.py
builder2ibek/converters/TimingTemplates.py
builder2ibek/converters/__init__.py
builder2ibek/converters/adUtil.py
builder2ibek/converters/asyn.py
builder2ibek/converters/autosave.py
builder2ibek/converters/cmsIon.py
builder2ibek/converters/deviocstats.py
builder2ibek/converters/digitelMpc.py
builder2ibek/converters/dlsPLC.py
builder2ibek/converters/epics_base.py
builder2ibek/converters/ffmpegServer.py
builder2ibek/converters/filters.py
builder2ibek/converters/gdaPlugins.yaml
builder2ibek/converters/globalHandler.py
builder2ibek/converters/interlock.py
builder2ibek/converters/ipac.py
builder2ibek/converters/mks937a.py
builder2ibek/converters/mks937b.py
builder2ibek/converters/mrfTiming.py
builder2ibek/converters/mxEH.py
builder2ibek/converters/pmac.py
builder2ibek/converters/pmacUtil.py
builder2ibek/converters/positioner.py
builder2ibek/converters/pvlogging.py
builder2ibek/converters/quadEM.py
builder2ibek/converters/rackfan.py
builder2ibek/converters/records.py
builder2ibek/converters/rga.py
builder2ibek/converters/terminalserver.py
builder2ibek/converters/tpmac.py
builder2ibek/converters/vacuumSpace.py
builder2ibek/converters/vacuumValve.py
builder2ibek/converters/water.py
builder2ibek-1.1.1.dist-info/licenses/LICENSE
builder2ibek-1.1.1.dist-info/METADATA
builder2ibek-1.1.1.dist-info/WHEEL
builder2ibek-1.1.1.dist-info/entry_points.txt
builder2ibek-1.1.1.dist-info/top_level.txt
builder2ibek-1.1.1.dist-info/RECORD
