Metadata-Version: 2.4
Name: builder2ibek
Version: 1.1.1
Summary: Conversion tool for DLS XML builder IOC instances to ibek ioc.yaml
Author-email: Giles Knap <giles.knap@diamond.ac.uk>
License:                                  Apache License
Project-URL: GitHub, https://github.com/epics-containers/builder2ibek
Classifier: Development Status :: 3 - Alpha
Classifier: License :: OSI Approved :: Apache Software License
Classifier: Programming Language :: Python :: 3.11
Classifier: Programming Language :: Python :: 3.12
Classifier: Programming Language :: Python :: 3.13
Requires-Python: >=3.11
License-File: LICENSE
Requires-Dist: ibek
Dynamic: license-file
